MANIFEST.in
Pipfile
README.md
requirements.txt
setup.cfg
setup.py
src/apistellar_cas/__init__.py
src/apistellar_cas/routing.py
src/apistellar_cas.egg-info/PKG-INFO
src/apistellar_cas.egg-info/SOURCES.txt
src/apistellar_cas.egg-info/dependency_links.txt
src/apistellar_cas.egg-info/requires.txt
src/apistellar_cas.egg-info/top_level.txt
src/apistellar_cas.egg-info/zip-safe