Metadata-Version: 2.1
Name: apistellar-cas
Version: 0.0.1
Summary: cas for apistellar
Home-page: https://www.github.com/ShichaoMa/apistellar-cas
Author: cn
Author-email: cnaafhvk@foxmail.com
License: MIT
Keywords: cas apistellar
Platform: UNKNOWN
Classifier: License :: OSI Approved :: MIT License
Classifier: Programming Language :: Python :: 3.6
Classifier: Intended Audience :: Developers
Classifier: Operating System :: Unix
